easy_debug/__init__.py
easy_debug/debug.py
easy_debug-0.0.2.dist-info/METADATA
easy_debug-0.0.2.dist-info/WHEEL
easy_debug-0.0.2.dist-info/top_level.txt
easy_debug-0.0.2.dist-info/RECORD
